{
  "@id": "https://data.datatourisme.fr/26/b39cb7e4-fb37-338b-a359-b2432f1cd0ac",
  "dc:identifier": "PCU0000000001378",
  "@type": [
    "CulturalSite",
    "PlaceOfInterest",
    "PointOfInterest"
  ],
  "rdfs:comment": {
    "de": [
      "Entdecken Sie die Stadt Sainte Ménehould und die Schätze, die es dort gibt, mit erfahrenen Führern!\n\nFührungen sind im Sommer jeden Freitagnachmittag und das ganze Jahr über auf Anfrage möglich\n\nEin Heft mit Führungen ist auch im Geschäft erhältlich.Entdecken Sie die Architektur des 18. Jahrhunderts, die Geschichte, die mit der Geschichte Frankreichs verbunden ist, Louis XVI, Dom Pérignon, Ménehould\n\nEs ist möglich, die Kirche Notre Dame und das Schloss zu besichtigen."
    ],
    "en": [
      "Discover the town’s 18th-century architecture and its history closely linked to the history of France, Louis XVI, Dom Pérignon and St Ménehould. The Church of Notre-Dame and the chateau are open to the public."
    ],
    "it": [
      "Venite a scoprire la città di Sainte Ménehould e i suoi tesori con guide esperte!\n\nVisita guidata possibile ogni venerdì pomeriggio in estate e tutto l'anno su richiesta\n\nScoprite l'architettura del XVIII secolo, la storia legata alla storia della Francia, Luigi XVI, Dom Pérignon, Ménehould\n\nÈ possibile visitare la chiesa di Notre Dame e il Castello."
    ],
    "fr": [
      "Venez découvrir la ville de Sainte Ménehould et les trésors qui s'y trouvent avec des guides expérimentés ! \n\nVisite guidée possible tous les vendredis après-midi en été et toute l'année sur demande. \n\nUn livret de visite guidée est également disponible en boutique.Découvrez l'architecture du XVIIIème siècle, l'histoire rattachée à l'histoire de France, Louis XVI, Dom Pérignon, Ménehould. \n\nIl est possible de visiter l'église Notre Dame et le Château."
    ],
    "es": [
      "Venga a descubrir la ciudad de Sainte Ménehould y sus tesoros con guías experimentados\n\nPosibilidad de visita guiada todos los viernes por la tarde en verano y todo el año previa solicitud\n\nDescubra la arquitectura del siglo XVIII, la historia ligada a la historia de Francia, Luis XVI, Dom Pérignon, Ménehould\n\nEs posible visitar la iglesia de Notre Dame y el Château."
    ],
    "nl": [
      "Kom de stad Sainte Ménehould en haar schatten ontdekken met ervaren gidsen!\n\nRondleiding mogelijk elke vrijdagmiddag in de zomer en het hele jaar door op aanvraag\n\nOntdek de 18e eeuwse architectuur, de geschiedenis verbonden met de geschiedenis van Frankrijk, Louis XVI, Dom Pérignon, Ménehould\n\nHet is mogelijk om de kerk Notre Dame en het kasteel te bezoeken."
    ]
  },
  "rdfs:label": {
    "en": [
      "Visite historique de la Ville de Sainte-Ménehould , une rue , une histoire"
    ],
    "fr": [
      "Visite historique de la Ville de Sainte-Ménehould , une rue , une histoire"
    ]
  },
  "hasBeenCreatedBy": {
    "@id": "https://data.datatourisme.fr/62473075-0f20-357e-b003-5489de342a25",
    "schema:legalName": "Office de tourisme Couleurs d'Argonne",
    "@type": [
      "schema:Organization",
      "foaf:Agent",
      "Agent"
    ]
  },
  "hasBeenPublishedBy": [
    {
      "@id": "https://data.datatourisme.fr/d4066567-1975-3d8e-907c-aa1f2adb0d5f",
      "schema:legalName": "S.I.T Partagé de la Marne",
      "@type": [
        "schema:Organization",
        "foaf:Agent",
        "Agent"
      ]
    }
  ],
  "hasContact": [
    {
      "@id": "https://data.datatourisme.fr/ea6b2c8c-fd8f-3642-9307-3e5f9240af8e",
      "schema:email": [
        "tourisme@argonne.fr"
      ],
      "schema:legalName": "Visite historique de la Ville de Sainte-Ménehould , une rue , une histoire",
      "schema:telephone": [
        "+33 3 26 60 85 83"
      ],
      "@type": [
        "schema:Organization",
        "foaf:Agent",
        "Agent"
      ],
      "foaf:homepage": [
        "http://www.argonne.fr/"
      ]
    }
  ],
  "hasDescription": [
    {
      "@id": "https://data.datatourisme.fr/5b71ff0f-0c37-3743-8777-aef3bfbe80f2",
      "@type": [
        "Description"
      ],
      "hasTranslatedProperty": [
        {
          "@id": "https://data.datatourisme.fr/29cdd1f5-3e53-32bb-97c1-a98f8fcb5030",
          "dc:contributor": [
            "https://api.deepl.com/v2/translate"
          ],
          "rdf:language": [
            "es"
          ],
          "rdf:predicate": [
            "shortDescription"
          ]
        },
        {
          "@id": "https://data.datatourisme.fr/83175475-494f-3d37-869e-2cd853e31a9c",
          "dc:contributor": [
            "https://api.deepl.com/v2/translate"
          ],
          "rdf:language": [
            "de"
          ],
          "rdf:predicate": [
            "shortDescription"
          ]
        },
        {
          "@id": "https://data.datatourisme.fr/9b6c86de-0d19-3fca-90cd-cff0dc83a017",
          "dc:contributor": [
            "https://api.deepl.com/v2/translate"
          ],
          "rdf:language": [
            "nl"
          ],
          "rdf:predicate": [
            "shortDescription"
          ]
        },
        {
          "@id": "https://data.datatourisme.fr/b8b6cadc-ab8a-3e85-a4e2-c18b8b213115",
          "dc:contributor": [
            "https://api.deepl.com/v2/translate"
          ],
          "rdf:language": [
            "it"
          ],
          "rdf:predicate": [
            "shortDescription"
          ]
        }
      ],
      "shortDescription": {
        "de": [
          "Entdecken Sie die Stadt Sainte Ménehould und die Schätze, die es dort gibt, mit erfahrenen Führern!\n\nFührungen sind im Sommer jeden Freitagnachmittag und das ganze Jahr über auf Anfrage möglich\n\nEin Heft mit Führungen ist auch im Geschäft erhältlich.Entdecken Sie die Architektur des 18. Jahrhunderts, die Geschichte, die mit der Geschichte Frankreichs verbunden ist, Louis XVI, Dom Pérignon, Ménehould\n\nEs ist möglich, die Kirche Notre Dame und das Schloss zu besichtigen."
        ],
        "en": [
          "Discover the town’s 18th-century architecture and its history closely linked to the history of France, Louis XVI, Dom Pérignon and St Ménehould. The Church of Notre-Dame and the chateau are open to the public."
        ],
        "it": [
          "Venite a scoprire la città di Sainte Ménehould e i suoi tesori con guide esperte!\n\nVisita guidata possibile ogni venerdì pomeriggio in estate e tutto l'anno su richiesta\n\nScoprite l'architettura del XVIII secolo, la storia legata alla storia della Francia, Luigi XVI, Dom Pérignon, Ménehould\n\nÈ possibile visitare la chiesa di Notre Dame e il Castello."
        ],
        "fr": [
          "Venez découvrir la ville de Sainte Ménehould et les trésors qui s'y trouvent avec des guides expérimentés ! \n\nVisite guidée possible tous les vendredis après-midi en été et toute l'année sur demande. \n\nUn livret de visite guidée est également disponible en boutique.Découvrez l'architecture du XVIIIème siècle, l'histoire rattachée à l'histoire de France, Louis XVI, Dom Pérignon, Ménehould. \n\nIl est possible de visiter l'église Notre Dame et le Château."
        ],
        "es": [
          "Venga a descubrir la ciudad de Sainte Ménehould y sus tesoros con guías experimentados\n\nPosibilidad de visita guiada todos los viernes por la tarde en verano y todo el año previa solicitud\n\nDescubra la arquitectura del siglo XVIII, la historia ligada a la historia de Francia, Luis XVI, Dom Pérignon, Ménehould\n\nEs posible visitar la iglesia de Notre Dame y el Château."
        ],
        "nl": [
          "Kom de stad Sainte Ménehould en haar schatten ontdekken met ervaren gidsen!\n\nRondleiding mogelijk elke vrijdagmiddag in de zomer en het hele jaar door op aanvraag\n\nOntdek de 18e eeuwse architectuur, de geschiedenis verbonden met de geschiedenis van Frankrijk, Louis XVI, Dom Pérignon, Ménehould\n\nHet is mogelijk om de kerk Notre Dame en het kasteel te bezoeken."
        ]
      }
    }
  ],
  "hasRepresentation": [
    {
      "@id": "https://data.datatourisme.fr/e49185aa-128e-37e0-b521-d64f53a22a5f",
      "ebucore:hasAnnotation": [
        {
          "@id": "https://data.datatourisme.fr/18cb4867-2de0-3b4d-b426-f1fa3ae51527",
          "@type": [
            "ebucore:Annotation"
          ],
          "credits": [
            "ot menou"
          ]
        }
      ],
      "ebucore:hasRelatedResource": [
        {
          "@id": "https://data.datatourisme.fr/0ed16d28-0fc5-39a4-ad2c-60522190a3c0",
          "ebucore:locator": [
            "http://cdt51.media.tourinsoft.eu/upload/DSC-0974.JPG"
          ],
          "@type": [
            "ebucore:Resource"
          ]
        }
      ],
      "@type": [
        "ebucore:EditorialObject"
      ]
    }
  ],
  "hasTranslatedProperty": [
    {
      "@id": "https://data.datatourisme.fr/0b1f7497-6985-3016-b012-f88328ea32e0",
      "dc:contributor": [
        "https://api.deepl.com/v2/translate"
      ],
      "rdf:language": [
        "it"
      ],
      "rdf:predicate": [
        {
          "@id": "rdfs:comment"
        }
      ]
    },
    {
      "@id": "https://data.datatourisme.fr/1870c6f9-9c93-381d-b8d7-5f4b058d0d00",
      "dc:contributor": [
        "https://api.deepl.com/v2/translate"
      ],
      "rdf:language": [
        "de"
      ],
      "rdf:predicate": [
        {
          "@id": "rdfs:comment"
        }
      ]
    },
    {
      "@id": "https://data.datatourisme.fr/2d0504bd-99ce-35d3-a16e-f2b5eeb9922b",
      "dc:contributor": [
        "https://api.deepl.com/v2/translate"
      ],
      "rdf:language": [
        "es"
      ],
      "rdf:predicate": [
        {
          "@id": "rdfs:comment"
        }
      ]
    },
    {
      "@id": "https://data.datatourisme.fr/9fec2a18-474b-3490-a3a4-1e7e6c4f98aa",
      "dc:contributor": [
        "https://api.deepl.com/v2/translate"
      ],
      "rdf:language": [
        "nl"
      ],
      "rdf:predicate": [
        {
          "@id": "rdfs:comment"
        }
      ]
    }
  ],
  "isLocatedAt": [
    {
      "@id": "https://data.datatourisme.fr/f1e2a441-cacc-3fdf-a2ab-80143c4ea297",
      "schema:address": [
        {
          "@id": "https://data.datatourisme.fr/a41b3013-960d-3c3b-a08d-38853676318a",
          "schema:addressLocality": "Sainte-Menehould",
          "schema:postalCode": "51800",
          "schema:streetAddress": [
            "15 place du Général Leclerc",
            "Office de Tourisme du Pays d'Argonne"
          ],
          "@type": [
            "schema:PostalAddress",
            "PostalAddress"
          ],
          "hasAddressCity": {
            "@id": "kb:51507",
            "@type": [
              "City"
            ],
            "rdfs:label": {
              "de": [
                "Sainte-Menehould"
              ],
              "pt": [
                "Sainte-Menehould"
              ],
              "en": [
                "Sainte-Menehould"
              ],
              "it": [
                "Sainte-Menehould"
              ],
              "fr": [
                "Sainte-Menehould"
              ],
              "nl": [
                "Sainte-Menehould"
              ],
              "es": [
                "Sainte-Menehould"
              ]
            },
            "insee": "51507",
            "isPartOfDepartment": {
              "@id": "kb:France4451",
              "@type": [
                "Department"
              ],
              "rdfs:label": {
                "de": [
                  "Marne"
                ],
                "pt": [
                  "Marne"
                ],
                "en": [
                  "Marne"
                ],
                "it": [
                  "Marne"
                ],
                "fr": [
                  "Marne"
                ],
                "nl": [
                  "Marne"
                ],
                "es": [
                  "Marne"
                ]
              },
              "insee": "51",
              "isPartOfRegion": {
                "@id": "kb:France44",
                "@type": [
                  "Region"
                ],
                "rdfs:label": {
                  "de": [
                    "Grand Est"
                  ],
                  "pt": [
                    "Grand Est"
                  ],
                  "en": [
                    "Grand Est"
                  ],
                  "it": [
                    "Grand Est"
                  ],
                  "fr": [
                    "Grand Est"
                  ],
                  "nl": [
                    "Grand Est"
                  ],
                  "es": [
                    "Grand Est"
                  ]
                },
                "insee": "44",
                "isPartOfCountry": {
                  "@id": "kb:France",
                  "@type": [
                    "schema:Country"
                  ],
                  "rdfs:label": {
                    "de": [
                      "France",
                      "Frankreich"
                    ],
                    "pt": [
                      "França",
                      "France"
                    ],
                    "en": [
                      "France"
                    ],
                    "it": [
                      "France",
                      "Francia"
                    ],
                    "fr": [
                      "France"
                    ],
                    "nl": [
                      "France",
                      "Frankrijk"
                    ],
                    "es": [
                      "France",
                      "Francia"
                    ]
                  }
                }
              }
            }
          }
        }
      ],
      "schema:geo": {
        "@id": "https://data.datatourisme.fr/6d7dc339-2c09-3948-9483-79b65631c724",
        "schema:latitude": "49.0919808",
        "schema:longitude": "4.89781672",
        "@type": [
          "schema:GeoCoordinates"
        ]
      },
      "schema:openingHoursSpecification": [
        {
          "@id": "https://data.datatourisme.fr/1d73794d-6f70-345e-84cd-afddb51493c6",
          "schema:closes": "12:00:00",
          "schema:dayOfWeek": [
            {
              "@id": "schema:Tuesday",
              "@type": [
                "schema:DayOfWeek"
              ],
              "rdfs:label": {
                "de": [
                  "Dienstag"
                ],
                "pt": [
                  "Terça-feira"
                ],
                "en": [
                  "Tuesday"
                ],
                "it": [
                  "Martedì"
                ],
                "fr": [
                  "Mardi"
                ],
                "es": [
                  "Martes"
                ],
                "nl": [
                  "Dinsdag"
                ]
              }
            }
          ],
          "schema:opens": "09:00:00",
          "schema:validFrom": "2023-01-01T00:00:00",
          "schema:validThrough": "2023-12-31T23:59:59",
          "@type": [
            "schema:OpeningHoursSpecification"
          ]
        },
        {
          "@id": "https://data.datatourisme.fr/1fb008aa-b730-3312-9e5d-13b3d0d3a6ce",
          "schema:closes": "12:00:00",
          "schema:dayOfWeek": [
            {
              "@id": "schema:Friday",
              "@type": [
                "schema:DayOfWeek"
              ],
              "rdfs:label": {
                "de": [
                  "Freitag"
                ],
                "pt": [
                  "Sexta-feira"
                ],
                "en": [
                  "Friday"
                ],
                "it": [
                  "Venerdì"
                ],
                "fr": [
                  "Vendredi"
                ],
                "nl": [
                  "Vrijdag"
                ],
                "es": [
                  "Viernes"
                ]
              }
            }
          ],
          "schema:opens": "09:00:00",
          "@type": [
            "schema:OpeningHoursSpecification"
          ]
        },
        {
          "@id": "https://data.datatourisme.fr/23b8294d-90df-362f-a5a0-04745f62a4d7",
          "schema:closes": "18:00:00",
          "schema:dayOfWeek": [
            {
              "@id": "schema:Friday",
              "@type": [
                "schema:DayOfWeek"
              ],
              "rdfs:label": {
                "de": [
                  "Freitag"
                ],
                "pt": [
                  "Sexta-feira"
                ],
                "en": [
                  "Friday"
                ],
                "it": [
                  "Venerdì"
                ],
                "fr": [
                  "Vendredi"
                ],
                "nl": [
                  "Vrijdag"
                ],
                "es": [
                  "Viernes"
                ]
              }
            }
          ],
          "schema:opens": "14:00:00",
          "schema:validFrom": "2023-01-01T00:00:00",
          "schema:validThrough": "2023-12-31T23:59:59",
          "@type": [
            "schema:OpeningHoursSpecification"
          ]
        },
        {
          "@id": "https://data.datatourisme.fr/299cd084-62c4-3b09-a76f-7709d2002a68",
          "schema:closes": "12:00:00",
          "schema:dayOfWeek": [
            {
              "@id": "schema:Tuesday",
              "@type": [
                "schema:DayOfWeek"
              ],
              "rdfs:label": {
                "de": [
                  "Dienstag"
                ],
                "pt": [
                  "Terça-feira"
                ],
                "en": [
                  "Tuesday"
                ],
                "it": [
                  "Martedì"
                ],
                "fr": [
                  "Mardi"
                ],
                "es": [
                  "Martes"
                ],
                "nl": [
                  "Dinsdag"
                ]
              }
            }
          ],
          "schema:opens": "09:00:00",
          "@type": [
            "schema:OpeningHoursSpecification"
          ]
        },
        {
          "@id": "https://data.datatourisme.fr/33aa0381-980d-31fd-a5b8-ff89f4335382",
          "schema:closes": "18:00:00",
          "schema:dayOfWeek": [
            {
              "@id": "schema:Friday",
              "@type": [
                "schema:DayOfWeek"
              ],
              "rdfs:label": {
                "de": [
                  "Freitag"
                ],
                "pt": [
                  "Sexta-feira"
                ],
                "en": [
                  "Friday"
                ],
                "it": [
                  "Venerdì"
                ],
                "fr": [
                  "Vendredi"
                ],
                "nl": [
                  "Vrijdag"
                ],
                "es": [
                  "Viernes"
                ]
              }
            }
          ],
          "schema:opens": "14:00:00",
          "@type": [
            "schema:OpeningHoursSpecification"
          ]
        },
        {
          "@id": "https://data.datatourisme.fr/3cb0c969-f963-33aa-ba71-1e865f3eae05",
          "schema:closes": "18:00:00",
          "schema:dayOfWeek": [
            {
              "@id": "schema:Thursday",
              "@type": [
                "schema:DayOfWeek"
              ],
              "rdfs:label": {
                "de": [
                  "Donnerstag"
                ],
                "pt": [
                  "Quinta-feira"
                ],
                "en": [
                  "Thursday"
                ],
                "it": [
                  "Giovedì"
                ],
                "fr": [
                  "Jeudi"
                ],
                "es": [
                  "Jueves"
                ],
                "nl": [
                  "Donderdag"
                ]
              }
            }
          ],
          "schema:opens": "14:00:00",
          "@type": [
            "schema:OpeningHoursSpecification"
          ]
        },
        {
          "@id": "https://data.datatourisme.fr/49923e7b-20de-3bf1-a132-a08bbfea48ca",
          "schema:closes": "18:00:00",
          "schema:dayOfWeek": [
            {
              "@id": "schema:Wednesday",
              "@type": [
                "schema:DayOfWeek"
              ],
              "rdfs:label": {
                "de": [
                  "Mittwoch"
                ],
                "pt": [
                  "Quarta-feira"
                ],
                "en": [
                  "Wednesday"
                ],
                "it": [
                  "Mercoledì"
                ],
                "fr": [
                  "Mercredi"
                ],
                "nl": [
                  "Woensdag"
                ],
                "es": [
                  "Miércoles"
                ]
              }
            }
          ],
          "schema:opens": "14:00:00",
          "@type": [
            "schema:OpeningHoursSpecification"
          ]
        },
        {
          "@id": "https://data.datatourisme.fr/54185fa6-cbe0-3194-a316-7d1820614f87",
          "schema:closes": "17:00:00",
          "schema:dayOfWeek": [
            {
              "@id": "schema:Monday",
              "@type": [
                "schema:DayOfWeek"
              ],
              "rdfs:label": {
                "de": [
                  "Montag"
                ],
                "pt": [
                  "Segunda-feira"
                ],
                "en": [
                  "Monday"
                ],
                "it": [
                  "Lunedì"
                ],
                "fr": [
                  "Lundi"
                ],
                "nl": [
                  "Maandag"
                ],
                "es": [
                  "Lunes"
                ]
              }
            }
          ],
          "schema:opens": "14:00:00",
          "schema:validFrom": "2023-01-01T00:00:00",
          "schema:validThrough": "2023-12-31T23:59:59",
          "@type": [
            "schema:OpeningHoursSpecification"
          ]
        },
        {
          "@id": "https://data.datatourisme.fr/5482de31-4b26-33a6-910f-532421aad0c9",
          "schema:closes": "12:00:00",
          "schema:dayOfWeek": [
            {
              "@id": "schema:Friday",
              "@type": [
                "schema:DayOfWeek"
              ],
              "rdfs:label": {
                "de": [
                  "Freitag"
                ],
                "pt": [
                  "Sexta-feira"
                ],
                "en": [
                  "Friday"
                ],
                "it": [
                  "Venerdì"
                ],
                "fr": [
                  "Vendredi"
                ],
                "nl": [
                  "Vrijdag"
                ],
                "es": [
                  "Viernes"
                ]
              }
            }
          ],
          "schema:opens": "09:00:00",
          "schema:validFrom": "2023-01-01T00:00:00",
          "schema:validThrough": "2023-12-31T23:59:59",
          "@type": [
            "schema:OpeningHoursSpecification"
          ]
        },
        {
          "@id": "https://data.datatourisme.fr/595d4912-06a9-3c87-9e37-8d1f3d1afd7a",
          "schema:closes": "18:00:00",
          "schema:dayOfWeek": [
            {
              "@id": "schema:Tuesday",
              "@type": [
                "schema:DayOfWeek"
              ],
              "rdfs:label": {
                "de": [
                  "Dienstag"
                ],
                "pt": [
                  "Terça-feira"
                ],
                "en": [
                  "Tuesday"
                ],
                "it": [
                  "Martedì"
                ],
                "fr": [
                  "Mardi"
                ],
                "es": [
                  "Martes"
                ],
                "nl": [
                  "Dinsdag"
                ]
              }
            }
          ],
          "schema:opens": "14:00:00",
          "schema:validFrom": "2023-01-01T00:00:00",
          "schema:validThrough": "2023-12-31T23:59:59",
          "@type": [
            "schema:OpeningHoursSpecification"
          ]
        },
        {
          "@id": "https://data.datatourisme.fr/71e0d992-cc14-39ba-a3a6-5bc83f0cfd12",
          "schema:closes": "18:00:00",
          "schema:dayOfWeek": [
            {
              "@id": "schema:Tuesday",
              "@type": [
                "schema:DayOfWeek"
              ],
              "rdfs:label": {
                "de": [
                  "Dienstag"
                ],
                "pt": [
                  "Terça-feira"
                ],
                "en": [
                  "Tuesday"
                ],
                "it": [
                  "Martedì"
                ],
                "fr": [
                  "Mardi"
                ],
                "es": [
                  "Martes"
                ],
                "nl": [
                  "Dinsdag"
                ]
              }
            }
          ],
          "schema:opens": "14:00:00",
          "@type": [
            "schema:OpeningHoursSpecification"
          ]
        },
        {
          "@id": "https://data.datatourisme.fr/7733a349-8b75-3d23-9d34-9dbda529c14a",
          "schema:closes": "18:00:00",
          "schema:dayOfWeek": [
            {
              "@id": "schema:Monday",
              "@type": [
                "schema:DayOfWeek"
              ],
              "rdfs:label": {
                "de": [
                  "Montag"
                ],
                "pt": [
                  "Segunda-feira"
                ],
                "en": [
                  "Monday"
                ],
                "it": [
                  "Lunedì"
                ],
                "fr": [
                  "Lundi"
                ],
                "nl": [
                  "Maandag"
                ],
                "es": [
                  "Lunes"
                ]
              }
            }
          ],
          "schema:opens": "14:00:00",
          "@type": [
            "schema:OpeningHoursSpecification"
          ]
        },
        {
          "@id": "https://data.datatourisme.fr/9df68978-7581-3073-b642-1cfbe24b61a5",
          "schema:closes": "18:00:00",
          "schema:dayOfWeek": [
            {
              "@id": "schema:Saturday",
              "@type": [
                "schema:DayOfWeek"
              ],
              "rdfs:label": {
                "de": [
                  "Samstag"
                ],
                "pt": [
                  "Sábado"
                ],
                "en": [
                  "Saturday"
                ],
                "it": [
                  "Sabato"
                ],
                "fr": [
                  "Samedi"
                ],
                "nl": [
                  "Zaterdag"
                ],
                "es": [
                  "Sábado"
                ]
              }
            }
          ],
          "schema:opens": "14:00:00",
          "@type": [
            "schema:OpeningHoursSpecification"
          ]
        },
        {
          "@id": "https://data.datatourisme.fr/9ebd49a3-7bb9-362c-8334-0cdfd169ce05",
          "schema:closes": "12:00:00",
          "schema:dayOfWeek": [
            {
              "@id": "schema:Saturday",
              "@type": [
                "schema:DayOfWeek"
              ],
              "rdfs:label": {
                "de": [
                  "Samstag"
                ],
                "pt": [
                  "Sábado"
                ],
                "en": [
                  "Saturday"
                ],
                "it": [
                  "Sabato"
                ],
                "fr": [
                  "Samedi"
                ],
                "nl": [
                  "Zaterdag"
                ],
                "es": [
                  "Sábado"
                ]
              }
            }
          ],
          "schema:opens": "09:00:00",
          "schema:validFrom": "2023-01-01T00:00:00",
          "schema:validThrough": "2023-12-31T23:59:59",
          "@type": [
            "schema:OpeningHoursSpecification"
          ]
        },
        {
          "@id": "https://data.datatourisme.fr/a80c5dfb-e6fc-30b1-9bd7-17a4444b7155",
          "schema:closes": "12:00:00",
          "schema:dayOfWeek": [
            {
              "@id": "schema:Monday",
              "@type": [
                "schema:DayOfWeek"
              ],
              "rdfs:label": {
                "de": [
                  "Montag"
                ],
                "pt": [
                  "Segunda-feira"
                ],
                "en": [
                  "Monday"
                ],
                "it": [
                  "Lunedì"
                ],
                "fr": [
                  "Lundi"
                ],
                "nl": [
                  "Maandag"
                ],
                "es": [
                  "Lunes"
                ]
              }
            }
          ],
          "schema:opens": "09:00:00",
          "schema:validFrom": "2023-01-01T00:00:00",
          "schema:validThrough": "2023-12-31T23:59:59",
          "@type": [
            "schema:OpeningHoursSpecification"
          ]
        },
        {
          "@id": "https://data.datatourisme.fr/b7cda247-c832-3cac-b61b-f91e56d2573f",
          "schema:closes": "18:00:00",
          "schema:dayOfWeek": [
            {
              "@id": "schema:Thursday",
              "@type": [
                "schema:DayOfWeek"
              ],
              "rdfs:label": {
                "de": [
                  "Donnerstag"
                ],
                "pt": [
                  "Quinta-feira"
                ],
                "en": [
                  "Thursday"
                ],
                "it": [
                  "Giovedì"
                ],
                "fr": [
                  "Jeudi"
                ],
                "es": [
                  "Jueves"
                ],
                "nl": [
                  "Donderdag"
                ]
              }
            }
          ],
          "schema:opens": "14:00:00",
          "schema:validFrom": "2023-01-01T00:00:00",
          "schema:validThrough": "2023-12-31T23:59:59",
          "@type": [
            "schema:OpeningHoursSpecification"
          ]
        },
        {
          "@id": "https://data.datatourisme.fr/c69f8a9b-f474-3cbe-bfa3-f531803741d2",
          "schema:closes": "12:00:00",
          "schema:dayOfWeek": [
            {
              "@id": "schema:Wednesday",
              "@type": [
                "schema:DayOfWeek"
              ],
              "rdfs:label": {
                "de": [
                  "Mittwoch"
                ],
                "pt": [
                  "Quarta-feira"
                ],
                "en": [
                  "Wednesday"
                ],
                "it": [
                  "Mercoledì"
                ],
                "fr": [
                  "Mercredi"
                ],
                "nl": [
                  "Woensdag"
                ],
                "es": [
                  "Miércoles"
                ]
              }
            }
          ],
          "schema:opens": "09:00:00",
          "schema:validFrom": "2023-01-01T00:00:00",
          "schema:validThrough": "2023-12-31T23:59:59",
          "@type": [
            "schema:OpeningHoursSpecification"
          ]
        },
        {
          "@id": "https://data.datatourisme.fr/cbb35271-9361-3eed-8652-3293de9fc353",
          "schema:closes": "12:00:00",
          "schema:dayOfWeek": [
            {
              "@id": "schema:Saturday",
              "@type": [
                "schema:DayOfWeek"
              ],
              "rdfs:label": {
                "de": [
                  "Samstag"
                ],
                "pt": [
                  "Sábado"
                ],
                "en": [
                  "Saturday"
                ],
                "it": [
                  "Sabato"
                ],
                "fr": [
                  "Samedi"
                ],
                "nl": [
                  "Zaterdag"
                ],
                "es": [
                  "Sábado"
                ]
              }
            }
          ],
          "schema:opens": "09:00:00",
          "@type": [
            "schema:OpeningHoursSpecification"
          ]
        },
        {
          "@id": "https://data.datatourisme.fr/da087b82-703e-322b-898c-29afc5850a3b",
          "schema:closes": "12:00:00",
          "schema:dayOfWeek": [
            {
              "@id": "schema:Monday",
              "@type": [
                "schema:DayOfWeek"
              ],
              "rdfs:label": {
                "de": [
                  "Montag"
                ],
                "pt": [
                  "Segunda-feira"
                ],
                "en": [
                  "Monday"
                ],
                "it": [
                  "Lunedì"
                ],
                "fr": [
                  "Lundi"
                ],
                "nl": [
                  "Maandag"
                ],
                "es": [
                  "Lunes"
                ]
              }
            }
          ],
          "schema:opens": "09:00:00",
          "@type": [
            "schema:OpeningHoursSpecification"
          ]
        },
        {
          "@id": "https://data.datatourisme.fr/e23e7c35-12f0-3817-9e77-caef0218f4ea",
          "schema:closes": "12:00:00",
          "schema:dayOfWeek": [
            {
              "@id": "schema:Thursday",
              "@type": [
                "schema:DayOfWeek"
              ],
              "rdfs:label": {
                "de": [
                  "Donnerstag"
                ],
                "pt": [
                  "Quinta-feira"
                ],
                "en": [
                  "Thursday"
                ],
                "it": [
                  "Giovedì"
                ],
                "fr": [
                  "Jeudi"
                ],
                "es": [
                  "Jueves"
                ],
                "nl": [
                  "Donderdag"
                ]
              }
            }
          ],
          "schema:opens": "09:00:00",
          "schema:validFrom": "2023-01-01T00:00:00",
          "schema:validThrough": "2023-12-31T23:59:59",
          "@type": [
            "schema:OpeningHoursSpecification"
          ]
        },
        {
          "@id": "https://data.datatourisme.fr/e4f60952-32f8-370d-886e-dcafaad4c10e",
          "schema:closes": "12:00:00",
          "schema:dayOfWeek": [
            {
              "@id": "schema:Thursday",
              "@type": [
                "schema:DayOfWeek"
              ],
              "rdfs:label": {
                "de": [
                  "Donnerstag"
                ],
                "pt": [
                  "Quinta-feira"
                ],
                "en": [
                  "Thursday"
                ],
                "it": [
                  "Giovedì"
                ],
                "fr": [
                  "Jeudi"
                ],
                "es": [
                  "Jueves"
                ],
                "nl": [
                  "Donderdag"
                ]
              }
            }
          ],
          "schema:opens": "09:00:00",
          "@type": [
            "schema:OpeningHoursSpecification"
          ]
        },
        {
          "@id": "https://data.datatourisme.fr/eeeb17d9-3171-3b2f-93ff-48cd8ed5504a",
          "schema:closes": "12:00:00",
          "schema:dayOfWeek": [
            {
              "@id": "schema:Wednesday",
              "@type": [
                "schema:DayOfWeek"
              ],
              "rdfs:label": {
                "de": [
                  "Mittwoch"
                ],
                "pt": [
                  "Quarta-feira"
                ],
                "en": [
                  "Wednesday"
                ],
                "it": [
                  "Mercoledì"
                ],
                "fr": [
                  "Mercredi"
                ],
                "nl": [
                  "Woensdag"
                ],
                "es": [
                  "Miércoles"
                ]
              }
            }
          ],
          "schema:opens": "09:00:00",
          "@type": [
            "schema:OpeningHoursSpecification"
          ]
        },
        {
          "@id": "https://data.datatourisme.fr/ef3df804-a6f7-3ce9-9b05-8bd5e7b56b53",
          "schema:closes": "18:00:00",
          "schema:dayOfWeek": [
            {
              "@id": "schema:Wednesday",
              "@type": [
                "schema:DayOfWeek"
              ],
              "rdfs:label": {
                "de": [
                  "Mittwoch"
                ],
                "pt": [
                  "Quarta-feira"
                ],
                "en": [
                  "Wednesday"
                ],
                "it": [
                  "Mercoledì"
                ],
                "fr": [
                  "Mercredi"
                ],
                "nl": [
                  "Woensdag"
                ],
                "es": [
                  "Miércoles"
                ]
              }
            }
          ],
          "schema:opens": "14:00:00",
          "schema:validFrom": "2023-01-01T00:00:00",
          "schema:validThrough": "2023-12-31T23:59:59",
          "@type": [
            "schema:OpeningHoursSpecification"
          ]
        },
        {
          "@id": "https://data.datatourisme.fr/fdb00e85-6552-315d-801b-fddd11a47ec8",
          "schema:closes": "17:00:00",
          "schema:dayOfWeek": [
            {
              "@id": "schema:Saturday",
              "@type": [
                "schema:DayOfWeek"
              ],
              "rdfs:label": {
                "de": [
                  "Samstag"
                ],
                "pt": [
                  "Sábado"
                ],
                "en": [
                  "Saturday"
                ],
                "it": [
                  "Sabato"
                ],
                "fr": [
                  "Samedi"
                ],
                "nl": [
                  "Zaterdag"
                ],
                "es": [
                  "Sábado"
                ]
              }
            }
          ],
          "schema:opens": "14:00:00",
          "schema:validFrom": "2023-01-01T00:00:00",
          "schema:validThrough": "2023-12-31T23:59:59",
          "@type": [
            "schema:OpeningHoursSpecification"
          ]
        }
      ],
      "@type": [
        "schema:Place",
        "Place"
      ]
    }
  ],
  "lastUpdate": "2022-11-29",
  "lastUpdateDatatourisme": "2023-06-22T03:07:08.992Z",
  "offers": [
    {
      "@id": "https://data.datatourisme.fr/d15f9158-efd8-3ed3-bf7a-9e2223fe9d30",
      "schema:priceSpecification": [
        {
          "@id": "https://data.datatourisme.fr/008efbd3-553a-3963-adb5-1cbdc21d0577",
          "schema:maxPrice": [
            "2.5"
          ],
          "schema:minPrice": [
            "2.5"
          ],
          "schema:priceCurrency": "EUR",
          "@type": [
            "schema:PriceSpecification",
            "PriceSpecification"
          ],
          "hasEligiblePolicy": [
            {
              "@id": "kb:ChildRate",
              "@type": [
                "PricingPolicy"
              ],
              "rdfs:label": {
                "de": [
                  "Kindertarif"
                ],
                "pt": [
                  "Preço por criança"
                ],
                "en": [
                  "Child rate"
                ],
                "it": [
                  "Tariffa per bambini"
                ],
                "fr": [
                  "Tarif enfant"
                ],
                "es": [
                  "Tarifa infantil"
                ],
                "nl": [
                  "Kindertarief"
                ]
              }
            }
          ]
        },
        {
          "@id": "https://data.datatourisme.fr/365009f5-9514-356c-9114-41060e4f585d",
          "schema:maxPrice": [
            "7"
          ],
          "schema:minPrice": [
            "7"
          ],
          "schema:priceCurrency": "EUR",
          "@type": [
            "schema:PriceSpecification",
            "PriceSpecification"
          ],
          "hasEligiblePolicy": [
            {
              "@id": "kb:BaseRateFullRate",
              "@type": [
                "PricingPolicy"
              ],
              "rdfs:label": {
                "de": [
                  "Basistarif – voller Tarif"
                ],
                "pt": [
                  "Preço de base — preço total"
                ],
                "en": [
                  "Base rate - full rate"
                ],
                "it": [
                  "Tariffa di base — tariffa intera"
                ],
                "fr": [
                  "Tarif de base - plein tarif"
                ],
                "es": [
                  "Tarifa básica - tarifa completa"
                ],
                "nl": [
                  "Basistarief - vol tarief"
                ]
              }
            }
          ]
        },
        {
          "@id": "https://data.datatourisme.fr/e5a63607-8993-3dce-a856-6328d58b93e6",
          "schema:maxPrice": [
            "4"
          ],
          "schema:minPrice": [
            "4"
          ],
          "schema:priceCurrency": "EUR",
          "@type": [
            "schema:PriceSpecification",
            "PriceSpecification"
          ],
          "hasEligiblePolicy": [
            {
              "@id": "kb:Group",
              "@type": [
                "PricingPolicy"
              ],
              "rdfs:label": {
                "de": [
                  "Gruppentarif"
                ],
                "pt": [
                  "Preço para Grupos"
                ],
                "en": [
                  "Group rate"
                ],
                "it": [
                  "Tariffa per gruppi"
                ],
                "fr": [
                  "Tarif Groupe"
                ],
                "es": [
                  "Tarifa de grupo"
                ],
                "nl": [
                  "Groepstarief"
                ]
              }
            }
          ]
        }
      ],
      "@type": [
        "schema:Offer",
        "Offer"
      ]
    }
  ]
}