{
  "@id": "https://data.datatourisme.fr/13/88f0c660-9c0a-31fb-969f-c8a002607b80",
  "dc:identifier": "3947627",
  "@type": [
    "Church",
    "CulturalSite",
    "PlaceOfInterest",
    "PointOfInterest",
    "ReligiousSite"
  ],
  "rdfs:comment": {
    "de": [
      "Freie Besichtigung mit Dokument in Französisch oder Niederländisch\r\nJahrhundert mit vierjochigem Schiff, Seitenschiffen, nicht vorspringendem Querschiff, halbkreisförmiger Apsis und Apsis. Der Bau dieser Kirche erfolgte zeitlich gestaffelt."
    ],
    "en": [
      "Self-guided tour with documentation in French or Dutch\r\nA 12th century building with a nave of four bays, aisles, a non-protruding transept, apse and semi-circular apses. The construction of this church was staggered over time."
    ],
    "it": [
      "Visita autoguidata con documentazione in francese o olandese\r\nEdificio del XII secolo a tre navate, con transetto non sporgente, abside e absidi semicircolari. La costruzione di questa chiesa è stata scaglionata nel tempo."
    ],
    "fr": [
      "Visite libre avec document en français ou néerlandais. \r\nÉdifice du XIIe siècle à nef de quatre travées, bas côtés, transept non saillant, abside et absidioles en hémicycle. La construction de cette église s'est échelonnée dans le temps."
    ],
    "nl": [
      "Zelf rondleiding met documentatie in het Frans of Nederlands\r\nEen gebouw uit de 12e eeuw met een schip van vier traveeën, zijbeuken, een niet uitspringend dwarsschip, een apsis en halfronde absiden. De bouw van deze kerk was gespreid in de tijd."
    ],
    "es": [
      "Visita autoguiada con documentación en francés o neerlandés\r\nEdificio del siglo XII con una nave de cuatro tramos, naves, crucero no saliente, ábside y ábsides semicirculares. La construcción de esta iglesia se escalonó en el tiempo."
    ]
  },
  "rdfs:label": {
    "fr": [
      "Église Saint-Martin"
    ]
  },
  "hasBeenCreatedBy": {
    "@id": "https://data.datatourisme.fr/13/3d779cae-2d46-3f6a-8a99-a35ba4167977",
    "dc:identifier": "1336",
    "schema:email": [
      "office-moulins@allier-tourisme.net",
      "p.forichon@moulins-tourisme.com"
    ],
    "schema:legalName": "Office du tourisme de Moulins & sa région",
    "@type": [
      "schema:Organization",
      "foaf:Agent",
      "Agent"
    ],
    "foaf:homepage": [
      "http://www.moulins-tourisme.com/"
    ]
  },
  "hasBeenPublishedBy": [
    {
      "@id": "https://data.datatourisme.fr/8a9feb4b-2cbd-3d2c-b507-bd6c6776b23b",
      "schema:legalName": "Apidae Tourisme Scic SA - source : Apidae Tourisme",
      "@type": [
        "schema:Organization",
        "foaf:Agent",
        "Agent"
      ],
      "foaf:homepage": [
        "https://www.apidae-tourisme.com/"
      ]
    },
    {
      "@id": "https://data.datatourisme.fr/c55300f9-494b-38ba-adff-d663c77ad33a",
      "schema:legalName": "ALLIER BOURBONNAIS ATTRACTIVITÉ - source : Apidae Tourisme",
      "@type": [
        "schema:Organization",
        "foaf:Agent",
        "Agent"
      ],
      "foaf:homepage": [
        "https://www.apidae-tourisme.com/"
      ]
    }
  ],
  "hasContact": [
    {
      "@id": "https://data.datatourisme.fr/e1252b9c-3548-3b10-91eb-fbcfe002bf3f",
      "schema:email": [
        "besson.mairie@orange.fr"
      ],
      "schema:telephone": [
        "+33 4 70 42 81 74"
      ],
      "@type": [
        "foaf:Agent",
        "Agent"
      ],
      "foaf:homepage": [
        "http://www.besson.fr/"
      ]
    }
  ],
  "hasDescription": [
    {
      "@id": "https://data.datatourisme.fr/0593d68c-1a10-3a4c-9888-32d234009cdc",
      "@type": [
        "Description"
      ],
      "hasTranslatedProperty": [
        {
          "@id": "https://data.datatourisme.fr/90d5d879-9120-3d90-ba49-95e1552b662e",
          "dc:contributor": [
            "https://api.deepl.com/v2/translate"
          ],
          "rdf:language": [
            "it"
          ],
          "rdf:predicate": [
            "shortDescription"
          ]
        },
        {
          "@id": "https://data.datatourisme.fr/b3dfe694-0a86-3c8b-afdb-741afc7aae0b",
          "dc:contributor": [
            "https://api.deepl.com/v2/translate"
          ],
          "rdf:language": [
            "en"
          ],
          "rdf:predicate": [
            "shortDescription"
          ]
        },
        {
          "@id": "https://data.datatourisme.fr/be759cb8-8556-3453-b4b5-b146c2d4b565",
          "dc:contributor": [
            "https://api.deepl.com/v2/translate"
          ],
          "rdf:language": [
            "es"
          ],
          "rdf:predicate": [
            "shortDescription"
          ]
        },
        {
          "@id": "https://data.datatourisme.fr/d2c872cc-ca02-38ad-a958-d030c736a9ab",
          "dc:contributor": [
            "https://api.deepl.com/v2/translate"
          ],
          "rdf:language": [
            "de"
          ],
          "rdf:predicate": [
            "shortDescription"
          ]
        },
        {
          "@id": "https://data.datatourisme.fr/db058d9a-8057-39a2-b4cd-3c66ff057a55",
          "dc:contributor": [
            "https://api.deepl.com/v2/translate"
          ],
          "rdf:language": [
            "nl"
          ],
          "rdf:predicate": [
            "shortDescription"
          ]
        }
      ],
      "shortDescription": {
        "de": [
          "Freie Besichtigung mit Dokument in Französisch oder Niederländisch\r\nJahrhundert mit vierjochigem Schiff, Seitenschiffen, nicht vorspringendem Querschiff, halbkreisförmiger Apsis und Apsis. Der Bau dieser Kirche erfolgte zeitlich gestaffelt."
        ],
        "en": [
          "Self-guided tour with documentation in French or Dutch\r\nA 12th century building with a nave of four bays, aisles, a non-protruding transept, apse and semi-circular apses. The construction of this church was staggered over time."
        ],
        "it": [
          "Visita autoguidata con documentazione in francese o olandese\r\nEdificio del XII secolo a tre navate, con transetto non sporgente, abside e absidi semicircolari. La costruzione di questa chiesa è stata scaglionata nel tempo."
        ],
        "fr": [
          "Visite libre avec document en français ou néerlandais. \r\nÉdifice du XIIe siècle à nef de quatre travées, bas côtés, transept non saillant, abside et absidioles en hémicycle. La construction de cette église s'est échelonnée dans le temps."
        ],
        "nl": [
          "Zelf rondleiding met documentatie in het Frans of Nederlands\r\nEen gebouw uit de 12e eeuw met een schip van vier traveeën, zijbeuken, een niet uitspringend dwarsschip, een apsis en halfronde absiden. De bouw van deze kerk was gespreid in de tijd."
        ],
        "es": [
          "Visita autoguiada con documentación en francés o neerlandés\r\nEdificio del siglo XII con una nave de cuatro tramos, naves, crucero no saliente, ábside y ábsides semicirculares. La construcción de esta iglesia se escalonó en el tiempo."
        ]
      }
    }
  ],
  "hasTheme": [
    {
      "@id": "kb:Culture",
      "@type": [
        "CulturalTheme"
      ],
      "rdfs:label": {
        "de": [
          "Kultur"
        ],
        "pt": [
          "Cultura"
        ],
        "en": [
          "Culture"
        ],
        "it": [
          "Cultura"
        ],
        "fr": [
          "Culture"
        ],
        "nl": [
          "Cultuur"
        ],
        "es": [
          "Cultura"
        ]
      }
    }
  ],
  "hasTranslatedProperty": [
    {
      "@id": "https://data.datatourisme.fr/31ab9f39-15ce-3ee1-9b3c-78cff2380936",
      "dc:contributor": [
        "https://api.deepl.com/v2/translate"
      ],
      "rdf:language": [
        "en"
      ],
      "rdf:predicate": [
        {
          "@id": "rdfs:comment"
        }
      ]
    },
    {
      "@id": "https://data.datatourisme.fr/4c21bc9e-dcc8-37ce-be7d-72146f391eb6",
      "dc:contributor": [
        "https://api.deepl.com/v2/translate"
      ],
      "rdf:language": [
        "de"
      ],
      "rdf:predicate": [
        {
          "@id": "rdfs:comment"
        }
      ]
    },
    {
      "@id": "https://data.datatourisme.fr/5a696c01-78ba-332b-b2c8-4e704fa53fad",
      "dc:contributor": [
        "https://api.deepl.com/v2/translate"
      ],
      "rdf:language": [
        "es"
      ],
      "rdf:predicate": [
        {
          "@id": "rdfs:comment"
        }
      ]
    },
    {
      "@id": "https://data.datatourisme.fr/edf7115d-d8e2-3d45-9aae-090b45d96546",
      "dc:contributor": [
        "https://api.deepl.com/v2/translate"
      ],
      "rdf:language": [
        "it"
      ],
      "rdf:predicate": [
        {
          "@id": "rdfs:comment"
        }
      ]
    },
    {
      "@id": "https://data.datatourisme.fr/f83fe827-3639-3690-9028-18c93682a70e",
      "dc:contributor": [
        "https://api.deepl.com/v2/translate"
      ],
      "rdf:language": [
        "nl"
      ],
      "rdf:predicate": [
        {
          "@id": "rdfs:comment"
        }
      ]
    }
  ],
  "isLocatedAt": [
    {
      "@id": "https://data.datatourisme.fr/90e44884-fc36-39c6-8d92-f6aed2313202",
      "schema:address": [
        {
          "@id": "https://data.datatourisme.fr/d53e448d-00bd-347d-8cc2-b4a192c65c85",
          "schema:addressLocality": "Besson",
          "schema:postalCode": "03210",
          "schema:streetAddress": [
            "Le Bourg"
          ],
          "@type": [
            "schema:PostalAddress",
            "PostalAddress"
          ],
          "hasAddressCity": {
            "@id": "kb:03026",
            "@type": [
              "City"
            ],
            "rdfs:label": {
              "de": [
                "Besson"
              ],
              "pt": [
                "Besson"
              ],
              "en": [
                "Besson"
              ],
              "it": [
                "Besson"
              ],
              "fr": [
                "Besson"
              ],
              "nl": [
                "Besson"
              ],
              "es": [
                "Besson"
              ]
            },
            "insee": "03026",
            "isPartOfDepartment": {
              "@id": "kb:France8403",
              "@type": [
                "Department"
              ],
              "rdfs:label": {
                "de": [
                  "Allier"
                ],
                "pt": [
                  "Allier"
                ],
                "en": [
                  "Allier"
                ],
                "it": [
                  "Allier"
                ],
                "fr": [
                  "Allier"
                ],
                "nl": [
                  "Allier"
                ],
                "es": [
                  "Allier"
                ]
              },
              "insee": "03",
              "isPartOfRegion": {
                "@id": "kb:France84",
                "@type": [
                  "Region"
                ],
                "rdfs:label": {
                  "de": [
                    "Auvergne-Rhône-Alpes"
                  ],
                  "pt": [
                    "Auvergne-Rhône-Alpes"
                  ],
                  "en": [
                    "Auvergne-Rhône-Alpes"
                  ],
                  "it": [
                    "Auvergne-Rhône-Alpes"
                  ],
                  "fr": [
                    "Auvergne-Rhône-Alpes"
                  ],
                  "nl": [
                    "Auvergne-Rhône-Alpes"
                  ],
                  "es": [
                    "Auvergne-Rhône-Alpes"
                  ]
                },
                "insee": "84",
                "isPartOfCountry": {
                  "@id": "kb:France",
                  "@type": [
                    "schema:Country"
                  ],
                  "rdfs:label": {
                    "de": [
                      "France",
                      "Frankreich"
                    ],
                    "pt": [
                      "França",
                      "France"
                    ],
                    "en": [
                      "France"
                    ],
                    "it": [
                      "France",
                      "Francia"
                    ],
                    "fr": [
                      "France"
                    ],
                    "nl": [
                      "France",
                      "Frankrijk"
                    ],
                    "es": [
                      "France",
                      "Francia"
                    ]
                  }
                }
              }
            }
          }
        }
      ],
      "schema:geo": {
        "@id": "https://data.datatourisme.fr/df2651c2-b223-33c0-90a1-6a3d2bad5f9f",
        "schema:latitude": "46.469704",
        "schema:longitude": "3.263112",
        "@type": [
          "schema:GeoCoordinates"
        ]
      },
      "schema:openingHoursSpecification": [
        {
          "@id": "https://data.datatourisme.fr/68f1f6a6-decb-3d2e-9ec2-e0d8af72979a",
          "schema:closes": "18:00:00",
          "schema:opens": "09:00:00",
          "schema:validFrom": "2023-01-01T00:00:00",
          "schema:validThrough": "2023-12-31T23:59:59",
          "@type": [
            "schema:OpeningHoursSpecification"
          ]
        }
      ],
      "@type": [
        "schema:Place",
        "Place"
      ]
    }
  ],
  "isOwnedBy": [
    {
      "@id": "https://data.datatourisme.fr/88c77baf-badc-3a87-9305-38cb34e1ee31",
      "schema:email": [
        "office-moulins@allier-tourisme.net",
        "p.forichon@moulins-tourisme.com"
      ],
      "schema:legalName": "Office du tourisme de Moulins & sa région",
      "@type": [
        "schema:Organization",
        "foaf:Agent",
        "Agent"
      ],
      "foaf:homepage": [
        "http://www.moulins-tourisme.com/"
      ]
    }
  ],
  "lastUpdate": "2023-06-08",
  "lastUpdateDatatourisme": "2023-06-09T05:49:13.327Z"
}