{
  "@id": "https://data.datatourisme.fr/13/3a077059-44c4-34f1-98e9-26bcfebf2fc0",
  "dc:identifier": "888992",
  "@type": [
    "schema:LocalBusiness",
    "schema:Museum",
    "CulturalSite",
    "Museum",
    "PlaceOfInterest",
    "PointOfInterest"
  ],
  "rdfs:comment": {
    "de": [
      "Im Gebäude der alten Quelle Desaix, am Ufer der Morge, erzählen Tafeln die Geschichte verschiedener umliegender Quellen. Objekte und zugehörige Archive."
    ],
    "en": [
      "In the building of the old  Desaix water source, on the banks of the River Morge, you can find information panels relating the history of various surrounding sources. Objects of interest and related archives."
    ],
    "it": [
      "Nell'edificio dell'antica Source Desaix, sulle rive della Morge, pannelli che raccontano la storia di varie sorgenti circostanti. Oggetti e archivi correlati."
    ],
    "fr": [
      "Dans le bâtiment de l'ancienne Source Desaix, au bord de la Morge, panneaux relatant l'historique de différentes sources environnantes. Objets et archives s'y rapportant."
    ],
    "nl": [
      "In het gebouw van de voormalige Source Desaix, aan de oevers van de Morge, hangen panelen die de geschiedenis van verschillende bronnen in de omgeving weergeven. Verwante objecten en archieven."
    ],
    "es": [
      "En el edificio de la antigua Fuente Desaix, a orillas del Morge, paneles que relatan la historia de varias fuentes de los alrededores. Objetos y archivos relacionados."
    ]
  },
  "rdfs:label": {
    "en": [
      "Saint-Myon Springs Museum"
    ],
    "fr": [
      "Musée des Sources de Saint-Myon"
    ]
  },
  "hasBeenCreatedBy": {
    "@id": "https://data.datatourisme.fr/13/3e313b9b-adf1-3632-8dae-5452d20e1af6",
    "dc:identifier": "1351",
    "schema:email": [
      "eva.glasziou@tourisme-combrailles.fr",
      "evelyne.ceroni@tourisme-combrailles.fr",
      "melanie.mista@tourisme-combrailles.fr"
    ],
    "schema:legalName": "Office de Tourisme des Combrailles",
    "@type": [
      "schema:Organization",
      "foaf:Agent",
      "Agent"
    ],
    "foaf:homepage": [
      "https://www.tourisme-combrailles.fr/"
    ]
  },
  "hasBeenPublishedBy": [
    {
      "@id": "https://data.datatourisme.fr/8a9feb4b-2cbd-3d2c-b507-bd6c6776b23b",
      "schema:legalName": "Apidae Tourisme Scic SA - source : Apidae Tourisme",
      "@type": [
        "schema:Organization",
        "foaf:Agent",
        "Agent"
      ],
      "foaf:homepage": [
        "https://www.apidae-tourisme.com/"
      ]
    }
  ],
  "hasContact": [
    {
      "@id": "https://data.datatourisme.fr/cce37d8a-375e-3e51-8dfe-bdb0c648fabe",
      "schema:email": [
        "mairiestmyon@wanadoo.fr"
      ],
      "schema:telephone": [
        "+33 4 73 33 31 54"
      ],
      "@type": [
        "foaf:Agent",
        "Agent"
      ],
      "foaf:homepage": [
        "https://www.saint-myon.com/"
      ]
    }
  ],
  "hasDescription": [
    {
      "@id": "https://data.datatourisme.fr/2c500498-0592-3f62-bac1-b3ce96dcdd1a",
      "@type": [
        "Description"
      ],
      "hasTranslatedProperty": [
        {
          "@id": "https://data.datatourisme.fr/06fe8933-25bb-3756-847b-4b71e2595405",
          "dc:contributor": [
            "https://api.deepl.com/v2/translate"
          ],
          "rdf:language": [
            "nl"
          ],
          "rdf:predicate": [
            "shortDescription"
          ]
        },
        {
          "@id": "https://data.datatourisme.fr/353ebc95-d352-378f-b269-acd7f1b552ec",
          "dc:contributor": [
            "https://api.deepl.com/v2/translate"
          ],
          "rdf:language": [
            "it"
          ],
          "rdf:predicate": [
            "shortDescription"
          ]
        },
        {
          "@id": "https://data.datatourisme.fr/3febf65a-3c74-3b0c-9c94-9c381abe6aab",
          "dc:contributor": [
            "https://api.deepl.com/v2/translate"
          ],
          "rdf:language": [
            "es"
          ],
          "rdf:predicate": [
            "shortDescription"
          ]
        }
      ],
      "shortDescription": {
        "de": [
          "Im Gebäude der alten Quelle Desaix, am Ufer der Morge, erzählen Tafeln die Geschichte verschiedener umliegender Quellen. Objekte und zugehörige Archive."
        ],
        "en": [
          "In the building of the old  Desaix water source, on the banks of the River Morge, you can find information panels relating the history of various surrounding sources. Objects of interest and related archives."
        ],
        "it": [
          "Nell'edificio dell'antica Source Desaix, sulle rive della Morge, pannelli che raccontano la storia di varie sorgenti circostanti. Oggetti e archivi correlati."
        ],
        "fr": [
          "Dans le bâtiment de l'ancienne Source Desaix, au bord de la Morge, panneaux relatant l'historique de différentes sources environnantes. Objets et archives s'y rapportant."
        ],
        "nl": [
          "In het gebouw van de voormalige Source Desaix, aan de oevers van de Morge, hangen panelen die de geschiedenis van verschillende bronnen in de omgeving weergeven. Verwante objecten en archieven."
        ],
        "es": [
          "En el edificio de la antigua Fuente Desaix, a orillas del Morge, paneles que relatan la historia de varias fuentes de los alrededores. Objetos y archivos relacionados."
        ]
      }
    }
  ],
  "hasTheme": [
    {
      "@id": "kb:Culture",
      "@type": [
        "CulturalTheme"
      ],
      "rdfs:label": {
        "de": [
          "Kultur"
        ],
        "pt": [
          "Cultura"
        ],
        "en": [
          "Culture"
        ],
        "it": [
          "Cultura"
        ],
        "fr": [
          "Culture"
        ],
        "nl": [
          "Cultuur"
        ],
        "es": [
          "Cultura"
        ]
      }
    }
  ],
  "hasTranslatedProperty": [
    {
      "@id": "https://data.datatourisme.fr/1837362b-0e68-350e-b5f2-bf5070d91738",
      "dc:contributor": [
        "https://api.deepl.com/v2/translate"
      ],
      "rdf:language": [
        "it"
      ],
      "rdf:predicate": [
        {
          "@id": "rdfs:comment"
        }
      ]
    },
    {
      "@id": "https://data.datatourisme.fr/6c190005-fc88-3b5d-8735-1fc58180bcef",
      "dc:contributor": [
        "https://api.deepl.com/v2/translate"
      ],
      "rdf:language": [
        "es"
      ],
      "rdf:predicate": [
        {
          "@id": "rdfs:comment"
        }
      ]
    },
    {
      "@id": "https://data.datatourisme.fr/f97f83aa-9fa0-3c90-a142-f60e625c9823",
      "dc:contributor": [
        "https://api.deepl.com/v2/translate"
      ],
      "rdf:language": [
        "nl"
      ],
      "rdf:predicate": [
        {
          "@id": "rdfs:comment"
        }
      ]
    }
  ],
  "isLocatedAt": [
    {
      "@id": "https://data.datatourisme.fr/88e9a9f0-1b0f-36c4-8c58-f142089680cb",
      "schema:address": [
        {
          "@id": "https://data.datatourisme.fr/306eeef9-e881-3d9e-941d-06b44e764a6d",
          "schema:addressLocality": "Saint-Myon",
          "schema:postalCode": "63460",
          "schema:streetAddress": [
            "Chemin des Chabanettes"
          ],
          "@type": [
            "schema:PostalAddress",
            "PostalAddress"
          ],
          "hasAddressCity": {
            "@id": "kb:63379",
            "@type": [
              "City"
            ],
            "rdfs:label": {
              "de": [
                "Saint-Myon"
              ],
              "pt": [
                "Saint-Myon"
              ],
              "en": [
                "Saint-Myon"
              ],
              "it": [
                "Saint-Myon"
              ],
              "fr": [
                "Saint-Myon"
              ],
              "nl": [
                "Saint-Myon"
              ],
              "es": [
                "Saint-Myon"
              ]
            },
            "insee": "63379",
            "isPartOfDepartment": {
              "@id": "kb:France8463",
              "@type": [
                "Department"
              ],
              "rdfs:label": {
                "de": [
                  "Puy-de-Dôme"
                ],
                "pt": [
                  "Puy-de-Dôme"
                ],
                "en": [
                  "Puy-de-Dôme"
                ],
                "it": [
                  "Puy-de-Dôme"
                ],
                "fr": [
                  "Puy-de-Dôme"
                ],
                "nl": [
                  "Puy-de-Dôme"
                ],
                "es": [
                  "Puy-de-Dôme"
                ]
              },
              "insee": "63",
              "isPartOfRegion": {
                "@id": "kb:France84",
                "@type": [
                  "Region"
                ],
                "rdfs:label": {
                  "de": [
                    "Auvergne-Rhône-Alpes"
                  ],
                  "pt": [
                    "Auvergne-Rhône-Alpes"
                  ],
                  "en": [
                    "Auvergne-Rhône-Alpes"
                  ],
                  "it": [
                    "Auvergne-Rhône-Alpes"
                  ],
                  "fr": [
                    "Auvergne-Rhône-Alpes"
                  ],
                  "nl": [
                    "Auvergne-Rhône-Alpes"
                  ],
                  "es": [
                    "Auvergne-Rhône-Alpes"
                  ]
                },
                "insee": "84",
                "isPartOfCountry": {
                  "@id": "kb:France",
                  "@type": [
                    "schema:Country"
                  ],
                  "rdfs:label": {
                    "de": [
                      "France",
                      "Frankreich"
                    ],
                    "pt": [
                      "França",
                      "France"
                    ],
                    "en": [
                      "France"
                    ],
                    "it": [
                      "France",
                      "Francia"
                    ],
                    "fr": [
                      "France"
                    ],
                    "nl": [
                      "France",
                      "Frankrijk"
                    ],
                    "es": [
                      "France",
                      "Francia"
                    ]
                  }
                }
              }
            }
          }
        }
      ],
      "schema:geo": {
        "@id": "https://data.datatourisme.fr/68abc0e2-a700-3f3f-b23b-6df621c9ca6b",
        "schema:elevation": "360",
        "schema:latitude": "45.99556",
        "schema:longitude": "3.134067",
        "@type": [
          "schema:GeoCoordinates"
        ]
      },
      "schema:openingHoursSpecification": [
        {
          "@id": "https://data.datatourisme.fr/e6572210-cf51-3b5d-8032-7cca8ed3b3c4",
          "schema:validFrom": "2023-03-01T00:00:00",
          "schema:validThrough": "2023-11-30T23:59:59",
          "@type": [
            "schema:OpeningHoursSpecification"
          ]
        }
      ],
      "@type": [
        "schema:Place",
        "Place"
      ]
    }
  ],
  "isOwnedBy": [
    {
      "@id": "https://data.datatourisme.fr/84571c38-4128-364e-9fff-f891bc6d9407",
      "schema:email": [
        "eva.glasziou@tourisme-combrailles.fr",
        "evelyne.ceroni@tourisme-combrailles.fr",
        "melanie.mista@tourisme-combrailles.fr"
      ],
      "schema:legalName": "Office de Tourisme des Combrailles",
      "@type": [
        "schema:Organization",
        "foaf:Agent",
        "Agent"
      ],
      "foaf:homepage": [
        "https://www.tourisme-combrailles.fr/"
      ]
    }
  ],
  "lastUpdate": "2023-01-06",
  "lastUpdateDatatourisme": "2023-02-22T06:42:37.651Z"
}