{
  "@id": "https://data.datatourisme.fr/13/ffc09ddd-78ed-373c-a6b0-9d678c63078e",
  "dc:identifier": "811660",
  "@type": [
    "schema:LocalBusiness",
    "PlaceOfInterest",
    "PointOfInterest",
    "Store"
  ],
  "rdfs:comment": {
    "de": [
      "Das Unternehmen Les Tisanes le Dauphin wurde 1953 in Buis-les-Baronnies gegründet. Alle unsere Kräuter- und Früchtetees sowie Tees sind biologisch zertifiziert und stehen für Qualitätsprodukte. Wir wählen einen Großteil der Pflanzen in Frankreich und aus fairem Handel aus."
    ],
    "en": [
      "The factory Tisanes le Dauphin saw the light of day in 1953, in Buis-les-Baronnies. Our herbal teas and teas are certified organic. We choose fair trade plants from France."
    ],
    "it": [
      "Nel 1953, a Buis-les-Baronnies, è stata creata l'azienda Tisanes le Dauphin. Tutte le nostre tisane, infusi e tè sono certificati biologici, garanzia di prodotti di qualità. Selezioniamo la maggior parte delle piante in Francia e nel commercio equo e solidale."
    ],
    "fr": [
      "C’est en 1953, à Buis-les-Baronnies que l’entreprise les Tisanes le Dauphin voit le jour. Toutes nos tisanes, infusions et thés sont certifiés bio gage de produits de qualité. Nous sélectionnons une majorité de plantes en France et en commerce équitable."
    ],
    "nl": [
      "In 1953 werd in Buis-les-Baronnies het bedrijf Tisanes le Dauphin opgericht. Al onze kruidentheeën, infusies en theeën zijn biologisch gecertificeerd, een garantie voor kwaliteitsproducten. Wij selecteren een meerderheid van de planten in Frankrijk en in eerlijke handel."
    ],
    "es": [
      "Fue en 1953, en Buis-les-Baronnies, cuando se creó la empresa Tisanes le Dauphin. Todas nuestras tisanas, infusiones y tés están certificados como ecológicos, una garantía de productos de calidad. Seleccionamos la mayoría de las plantas en Francia y en el comercio justo."
    ]
  },
  "rdfs:label": {
    "de": [
      "Le Dauphin"
    ],
    "ru": [
      "Le Dauphin"
    ],
    "en": [
      "Le Dauphin"
    ],
    "it": [
      "Le Dauphin"
    ],
    "fr": [
      "Tisanes le Dauphin"
    ],
    "nl": [
      "Tisanes Le Dauphin"
    ],
    "zh": [
      "Le Dauphin"
    ],
    "es": [
      "Le Dauphin"
    ]
  },
  "hasBeenCreatedBy": {
    "@id": "https://data.datatourisme.fr/13/bf822969-6f7a-3bb4-b00c-fddef19fa23f",
    "dc:identifier": "174",
    "schema:email": [
      "leonie@baronnies-tourisme.com",
      "marine@baronnies-tourisme.com",
      "mathilde@baronnies-tourisme.com",
      "nathalie@baronnies-tourisme.com",
      "noemie@baronnies-tourisme.com",
      "pascale@baronnies-tourisme.com"
    ],
    "schema:legalName": "Office de Tourisme des Baronnies en Drôme Provençale",
    "@type": [
      "schema:Organization",
      "foaf:Agent",
      "Agent"
    ],
    "foaf:homepage": [
      "http://baronnies-tourisme.com/"
    ]
  },
  "hasBeenPublishedBy": [
    {
      "@id": "https://data.datatourisme.fr/d48f2ccd-2357-3a8e-b949-cb8bf19a361f",
      "schema:legalName": "Agence d'Attractivité de la Drôme - source : Apidae Tourisme",
      "@type": [
        "schema:Organization",
        "foaf:Agent",
        "Agent"
      ],
      "foaf:homepage": [
        "https://www.apidae-tourisme.com/"
      ]
    }
  ],
  "hasContact": [
    {
      "@id": "https://data.datatourisme.fr/a59a0731-2e6b-32b9-8ccf-81a46ee36a57",
      "schema:email": [
        "contact@tisane-ledauphin.com"
      ],
      "schema:telephone": [
        "+33 4 75 28 01 08"
      ],
      "@type": [
        "foaf:Agent",
        "Agent"
      ],
      "foaf:homepage": [
        "https://tisane-ledauphin.com/"
      ]
    }
  ],
  "hasDescription": [
    {
      "@id": "https://data.datatourisme.fr/e891a078-290d-3337-a30e-1c61123c1b7f",
      "@type": [
        "Description"
      ],
      "hasTranslatedProperty": [
        {
          "@id": "https://data.datatourisme.fr/04eadde5-370f-38ea-aa28-e31a2e76ff5f",
          "dc:contributor": [
            "https://api.deepl.com/v2/translate"
          ],
          "rdf:language": [
            "es"
          ],
          "rdf:predicate": [
            "shortDescription"
          ]
        },
        {
          "@id": "https://data.datatourisme.fr/3db2f295-6ab9-3cd2-be55-c5719a40f3ab",
          "dc:contributor": [
            "https://api.deepl.com/v2/translate"
          ],
          "rdf:language": [
            "it"
          ],
          "rdf:predicate": [
            "shortDescription"
          ]
        },
        {
          "@id": "https://data.datatourisme.fr/d2e0e649-bac9-33be-9730-563a4e8c82fb",
          "dc:contributor": [
            "https://api.deepl.com/v2/translate"
          ],
          "rdf:language": [
            "de"
          ],
          "rdf:predicate": [
            "shortDescription"
          ]
        }
      ],
      "shortDescription": {
        "de": [
          "Das Unternehmen Les Tisanes le Dauphin wurde 1953 in Buis-les-Baronnies gegründet. Alle unsere Kräuter- und Früchtetees sowie Tees sind biologisch zertifiziert und stehen für Qualitätsprodukte. Wir wählen einen Großteil der Pflanzen in Frankreich und aus fairem Handel aus."
        ],
        "en": [
          "The factory Tisanes le Dauphin saw the light of day in 1953, in Buis-les-Baronnies. Our herbal teas and teas are certified organic. We choose fair trade plants from France."
        ],
        "it": [
          "Nel 1953, a Buis-les-Baronnies, è stata creata l'azienda Tisanes le Dauphin. Tutte le nostre tisane, infusi e tè sono certificati biologici, garanzia di prodotti di qualità. Selezioniamo la maggior parte delle piante in Francia e nel commercio equo e solidale."
        ],
        "fr": [
          "C’est en 1953, à Buis-les-Baronnies que l’entreprise les Tisanes le Dauphin voit le jour. Toutes nos tisanes, infusions et thés sont certifiés bio gage de produits de qualité. Nous sélectionnons une majorité de plantes en France et en commerce équitable."
        ],
        "nl": [
          "In 1953 werd in Buis-les-Baronnies het bedrijf Tisanes le Dauphin opgericht. Al onze kruidentheeën, infusies en theeën zijn biologisch gecertificeerd, een garantie voor kwaliteitsproducten. Wij selecteren een meerderheid van de planten in Frankrijk en in eerlijke handel."
        ],
        "es": [
          "Fue en 1953, en Buis-les-Baronnies, cuando se creó la empresa Tisanes le Dauphin. Todas nuestras tisanas, infusiones y tés están certificados como ecológicos, una garantía de productos de calidad. Seleccionamos la mayoría de las plantas en Francia y en el comercio justo."
        ]
      }
    }
  ],
  "hasTranslatedProperty": [
    {
      "@id": "https://data.datatourisme.fr/25122858-569c-3029-8bcd-71587e91580e",
      "dc:contributor": [
        "https://api.deepl.com/v2/translate"
      ],
      "rdf:language": [
        "de"
      ],
      "rdf:predicate": [
        {
          "@id": "rdfs:comment"
        }
      ]
    },
    {
      "@id": "https://data.datatourisme.fr/5a20546a-7010-331c-9bec-0352afceb0c4",
      "dc:contributor": [
        "https://api.deepl.com/v2/translate"
      ],
      "rdf:language": [
        "es"
      ],
      "rdf:predicate": [
        {
          "@id": "rdfs:comment"
        }
      ]
    },
    {
      "@id": "https://data.datatourisme.fr/678de989-83f0-3101-a262-a8b9c3041db2",
      "dc:contributor": [
        "https://api.deepl.com/v2/translate"
      ],
      "rdf:language": [
        "it"
      ],
      "rdf:predicate": [
        {
          "@id": "rdfs:comment"
        }
      ]
    }
  ],
  "isLocatedAt": [
    {
      "@id": "https://data.datatourisme.fr/3b56193b-0e85-345e-ba21-338accb76e1e",
      "schema:address": [
        {
          "@id": "https://data.datatourisme.fr/a7f6425b-c37b-370b-8d92-377a6eeba087",
          "schema:addressLocality": "Buis-les-Baronnies",
          "schema:postalCode": "26170",
          "schema:streetAddress": [
            "279 route de la ZA Lapalun"
          ],
          "@type": [
            "schema:PostalAddress",
            "PostalAddress"
          ],
          "hasAddressCity": {
            "@id": "kb:26063",
            "@type": [
              "City"
            ],
            "rdfs:label": {
              "de": [
                "Buis-les-Baronnies"
              ],
              "pt": [
                "Buis-les-Baronnies"
              ],
              "en": [
                "Buis-les-Baronnies"
              ],
              "it": [
                "Buis-les-Baronnies"
              ],
              "fr": [
                "Buis-les-Baronnies"
              ],
              "nl": [
                "Buis-les-Baronnies"
              ],
              "es": [
                "Buis-les-Baronnies"
              ]
            },
            "insee": "26063",
            "isPartOfDepartment": {
              "@id": "kb:France8426",
              "@type": [
                "Department"
              ],
              "rdfs:label": {
                "de": [
                  "Drôme"
                ],
                "pt": [
                  "Drôme"
                ],
                "en": [
                  "Drôme"
                ],
                "it": [
                  "Drôme"
                ],
                "fr": [
                  "Drôme"
                ],
                "nl": [
                  "Drôme"
                ],
                "es": [
                  "Drôme"
                ]
              },
              "insee": "26",
              "isPartOfRegion": {
                "@id": "kb:France84",
                "@type": [
                  "Region"
                ],
                "rdfs:label": {
                  "de": [
                    "Auvergne-Rhône-Alpes"
                  ],
                  "pt": [
                    "Auvergne-Rhône-Alpes"
                  ],
                  "en": [
                    "Auvergne-Rhône-Alpes"
                  ],
                  "it": [
                    "Auvergne-Rhône-Alpes"
                  ],
                  "fr": [
                    "Auvergne-Rhône-Alpes"
                  ],
                  "nl": [
                    "Auvergne-Rhône-Alpes"
                  ],
                  "es": [
                    "Auvergne-Rhône-Alpes"
                  ]
                },
                "insee": "84",
                "isPartOfCountry": {
                  "@id": "kb:France",
                  "@type": [
                    "schema:Country"
                  ],
                  "rdfs:label": {
                    "de": [
                      "France",
                      "Frankreich"
                    ],
                    "pt": [
                      "França",
                      "France"
                    ],
                    "en": [
                      "France"
                    ],
                    "it": [
                      "France",
                      "Francia"
                    ],
                    "fr": [
                      "France"
                    ],
                    "nl": [
                      "France",
                      "Frankrijk"
                    ],
                    "es": [
                      "France",
                      "Francia"
                    ]
                  }
                }
              }
            }
          }
        }
      ],
      "schema:geo": {
        "@id": "https://data.datatourisme.fr/23c37320-f547-3d06-8ce6-156901bb9541",
        "schema:elevation": "370",
        "schema:latitude": "44.263719",
        "schema:longitude": "5.26346",
        "@type": [
          "schema:GeoCoordinates"
        ]
      },
      "schema:openingHoursSpecification": [
        {
          "@id": "https://data.datatourisme.fr/f87e535a-636d-3343-ad63-8a03392e7511",
          "schema:validFrom": "2023-01-01T00:00:00",
          "schema:validThrough": "2023-12-31T23:59:59",
          "@type": [
            "schema:OpeningHoursSpecification"
          ]
        }
      ],
      "@type": [
        "schema:Place",
        "Place"
      ]
    }
  ],
  "isOwnedBy": [
    {
      "@id": "https://data.datatourisme.fr/74587bc9-d271-3ed3-8481-b15a03eff843",
      "schema:email": [
        "nathalie@baronnies-tourisme.com"
      ],
      "schema:legalName": "Office de Tourisme des Baronnies en Drôme Provençale",
      "@type": [
        "schema:Organization",
        "foaf:Agent",
        "Agent"
      ],
      "foaf:homepage": [
        "http://baronnies-tourisme.com/"
      ]
    }
  ],
  "lastUpdate": "2023-01-27",
  "lastUpdateDatatourisme": "2023-02-01T18:07:35.809Z"
}